dungeongen/__init__.py
dungeongen/constants.py
dungeongen/debug_config.py
dungeongen/debug_draw.py
dungeongen/logging_config.py
dungeongen/options.py
dungeongen/algorithms/__init__.py
dungeongen/algorithms/chaikin.py
dungeongen/algorithms/marching_squares.py
dungeongen/algorithms/poisson.py
dungeongen/algorithms/spacialhash.py
dungeongen/data/fonts/OFL.txt
dungeongen/data/fonts/RobotoCondensed-Regular.ttf
dungeongen/data/fonts/RobotoCondensed.ttf
dungeongen/drawing/__init__.py
dungeongen/drawing/crosshatch.py
dungeongen/drawing/crosshatch_tiled.py
dungeongen/drawing/water.py
dungeongen/graphics/__init__.py
dungeongen/graphics/aliases.py
dungeongen/graphics/conversions.py
dungeongen/graphics/lines.py
dungeongen/graphics/math.py
dungeongen/graphics/noise.py
dungeongen/graphics/rotation.py
dungeongen/graphics/shapes.py
dungeongen/layout/__init__.py
dungeongen/layout/generator.py
dungeongen/layout/models.py
dungeongen/layout/numbering.py
dungeongen/layout/occupancy.py
dungeongen/layout/params.py
dungeongen/layout/spatial.py
dungeongen/layout/svg.py
dungeongen/layout/validator.py
dungeongen/layout/water.py
dungeongen/map/__init__.py
dungeongen/map/arrange.py
dungeongen/map/door.py
dungeongen/map/enums.py
dungeongen/map/exit.py
dungeongen/map/grid.py
dungeongen/map/map.py
dungeongen/map/mapelement.py
dungeongen/map/occupancy.py
dungeongen/map/passage.py
dungeongen/map/props.py
dungeongen/map/region.py
dungeongen/map/room.py
dungeongen/map/water.py
dungeongen/map/water_layer.py
dungeongen/map/_arrange/__init__.py
dungeongen/map/_arrange/arrange_columns.py
dungeongen/map/_arrange/arrange_props.py
dungeongen/map/_arrange/arrange_utils.py
dungeongen/map/_arrange/proptypes.py
dungeongen/map/_props/__init__.py
dungeongen/map/_props/altar.py
dungeongen/map/_props/coffin.py
dungeongen/map/_props/column.py
dungeongen/map/_props/dias.py
dungeongen/map/_props/fountain.py
dungeongen/map/_props/prop.py
dungeongen/map/_props/rock.py
dungeongen/map/_props/stairs.py
dungeongen-0.1.14.dist-info/METADATA
dungeongen-0.1.14.dist-info/WHEEL
dungeongen-0.1.14.dist-info/licenses/LICENSE
dungeongen-0.1.14.dist-info/RECORD
