Metadata-Version: 2.4
Name: dungeongen
Version: 0.1.14
Summary: A procedural dungeon map generator for tabletop RPGs
Project-URL: Homepage, https://github.com/benjcooley/dungeongen
Project-URL: Repository, https://github.com/benjcooley/dungeongen
Author: Benjamin Cooley
License-Expression: MIT
License-File: LICENSE
Keywords: dungeon,generator,maps,procedural,rpg,tabletop
Classifier: Development Status :: 4 - Beta
Classifier: Intended Audience :: Developers
Classifier: License :: OSI Approved :: MIT License
Classifier: Programming Language :: Python :: 3
Classifier: Programming Language :: Python :: 3.10
Classifier: Programming Language :: Python :: 3.11
Classifier: Programming Language :: Python :: 3.12
Classifier: Topic :: Games/Entertainment :: Role-Playing
Requires-Python: >=3.10
Requires-Dist: flask>=2.0.0
Requires-Dist: numpy>=1.24.0
Requires-Dist: opensimplex>=0.4
Requires-Dist: rich>=13.0.0
Requires-Dist: skia-python>=87.0
Provides-Extra: dev
Requires-Dist: pyright>=1.1; extra == 'dev'
Requires-Dist: pytest>=7.0; extra == 'dev'
